{
  "kind": "singleType",
  "collectionName": "editorial_signals",
  "info": {
    "singularName": "editorial-signal",
    "pluralName": "editorial-signals",
    "displayName": "Urednički signal"
  },
  "options": {
    "draftAndPublish": false
  },
  "attributes": {
    "label": {
      "type": "string",
      "default": "UREDNIČKI SIGNAL"
    },
    "label_en": {
      "type": "string"
    },
    "label_tr": {
      "type": "string"
    },
    "label_fr": {
      "type": "string"
    },
    "label_de": {
      "type": "string"
    },
    "label_es": {
      "type": "string"
    },
    "label_el": {
      "type": "string"
    },
    "label_ar": {
      "type": "string"
    },
    "text": {
      "type": "text",
      "required": true
    },
    "text_en": {
      "type": "text"
    },
    "text_tr": {
      "type": "text"
    },
    "text_fr": {
      "type": "text"
    },
    "text_de": {
      "type": "text"
    },
    "text_es": {
      "type": "text"
    },
    "text_el": {
      "type": "text"
    },
    "text_ar": {
      "type": "text"
    },
    "author": {
      "type": "string"
    },
    "author_en": {
      "type": "string"
    },
    "author_tr": {
      "type": "string"
    },
    "author_fr": {
      "type": "string"
    },
    "author_de": {
      "type": "string"
    },
    "author_es": {
      "type": "string"
    },
    "author_el": {
      "type": "string"
    },
    "author_ar": {
      "type": "string"
    },
    "type": {
      "type": "enumeration",
      "enum": [
        "quote",
        "statement",
        "question",
        "manifesto"
      ],
      "default": "statement"
    },
    "source": {
      "type": "string"
    },
    "source_en": {
      "type": "string"
    },
    "source_tr": {
      "type": "string"
    },
    "source_fr": {
      "type": "string"
    },
    "source_de": {
      "type": "string"
    },
    "source_es": {
      "type": "string"
    },
    "source_el": {
      "type": "string"
    },
    "source_ar": {
      "type": "string"
    },
    "linkedArticle": {
      "type": "relation",
      "relation": "oneToOne",
      "target": "api::article.article"
    },
    "ctaLabel": {
      "type": "string",
      "default": "Pročitaj kontekst"
    },
    "ctaLabel_en": {
      "type": "string"
    },
    "ctaLabel_tr": {
      "type": "string"
    },
    "ctaLabel_fr": {
      "type": "string"
    },
    "ctaLabel_de": {
      "type": "string"
    },
    "ctaLabel_es": {
      "type": "string"
    },
    "ctaLabel_el": {
      "type": "string"
    },
    "ctaLabel_ar": {
      "type": "string"
    },
    "isActive": {
      "type": "boolean",
      "default": true
    },
    "priority": {
      "type": "integer"
    },
    "backgroundMode": {
      "type": "enumeration",
      "enum": [
        "yellow",
        "dark",
        "outline"
      ],
      "default": "yellow"
    },
    "updatedNote": {
      "type": "text"
    }
  }
}
